downloader.py
nmsi.py
nmsi-0.1.4.dist-info/licenses/LICENSE
nmsi-0.1.4.dist-info/METADATA
nmsi-0.1.4.dist-info/WHEEL
nmsi-0.1.4.dist-info/entry_points.txt
nmsi-0.1.4.dist-info/top_level.txt
nmsi-0.1.4.dist-info/RECORD
