Metadata-Version: 2.4
Name: nmsi
Version: 0.1.4
Summary: No More Search for Installation - Easy installation tool for open source software
Author-email: toru-nakai <toru-nakai@users.noreply.github.com>
License-Expression: Apache-2.0
Project-URL: Homepage, https://github.com/toru-nakai/nmsi
Project-URL: Repository, https://github.com/toru-nakai/nmsi
Project-URL: Bug Tracker, https://github.com/toru-nakai/nmsi/issues
Keywords: install,tool,snippet
Classifier: Development Status :: 3 - Alpha
Classifier: Intended Audience :: System Administrators
Classifier: Programming Language :: Python :: 3
Requires-Python: >=3.9
License-File: LICENSE
Dynamic: license-file
